{"stats":{"minecraft:custom":{"minecraft:time_since_rest":10245,"minecraft:sprint_one_cm":27508,"minecraft:damage_taken":760,"minecraft:walk_one_cm":50479,"minecraft:damage_dealt":103,"minecraft:interact_with_crafting_table":3,"minecraft:fly_one_cm":20435,"minecraft:open_chest":1,"minecraft:crouch_one_cm":148,"minecraft:play_one_minute":13602,"minecraft:deaths":2,"minecraft:sneak_time":21,"minecraft:walk_under_water_one_cm":292,"minecraft:jump":265,"minecraft:time_since_death":11091,"minecraft:walk_on_water_one_cm":186,"minecraft:sleep_in_bed":1,"minecraft:fall_one_cm":6490},"minecraft:killed_by":{"minecraft:skeleton":2},"minecraft:mined":{"minecraft:large_fern":2,"minecraft:spruce_planks":4,"minecraft:wheat":3,"minecraft:spruce_log":23,"minecraft:grass":6,"minecraft:spruce_leaves":26,"minecraft:wall_torch":2,"minecraft:fern":2},"minecraft:used":{"minecraft:wooden_axe":53,"minecraft:spruce_planks":4,"lycanitesmobs:raw_maka_meat":2,"minecraft:torch":2,"minecraft:crafting_table":1},"minecraft:picked_up":{"minecraft:wheat":4,"patchouli:guide_book":1,"minecraft:leather":3,"minecraft:torch":4,"minecraft:potato":1,"minecraft:spruce_sapling":1,"minecraft:spruce_log":22,"minecraft:armor_stand":1,"minecraft:pumpkin_seeds":1,"minecraft:wheat_seeds":14,"minecraft:spruce_planks":4,"minecraft:iron_helmet":1,"lycanitesmobs:raw_maka_meat":2},"minecraft:crafted":{"minecraft:crafting_table":1,"minecraft:spruce_planks":28,"minecraft:stick":4,"minecraft:wooden_pickaxe":1,"minecraft:wooden_axe":1,"minecraft:bread":1}},"DataVersion":2586}